zhuan/__init__.py
zhuan-0.1.1.dist-info/METADATA
zhuan-0.1.1.dist-info/WHEEL
zhuan-0.1.1.dist-info/RECORD
