Metadata-Version: 2.1
Name: zhuan
Version: 0.1.1
Summary: 
Author: Robert Wen
Author-email: robert@pinclr.com
Requires-Python: >=3.8,<4.0
Classifier: Programming Language :: Python :: 3
Classifier: Programming Language :: Python :: 3.8
Classifier: Programming Language :: Python :: 3.9
Classifier: Programming Language :: Python :: 3.10
Classifier: Programming Language :: Python :: 3.11
Requires-Dist: pygame (>=2.2.0,<3.0.0)
Requires-Dist: twine (>=4.0.2,<5.0.0)
